fast_thumbhash-1.0.0.dist-info/METADATA
fast_thumbhash-1.0.0.dist-info/WHEEL
fast_thumbhash/README.md
fast_thumbhash/__init__.py
fast_thumbhash/fast_thumbhash.cp311-win32.pyd
fast_thumbhash/wrappers.py
fast_thumbhash-1.0.0.dist-info/RECORD
