Metadata-Version: 2.4
Name: fast_thumbhash
Version: 1.0.0
Classifier: Programming Language :: Python :: 3
Classifier: Programming Language :: Rust
Classifier: Operating System :: OS Independent
Requires-Dist: pillow ; extra == 'pillow'
Provides-Extra: pillow
Summary: Fast ThumbHash bindings for Python using Rust (PyO3)
Author: Sita Berete
Requires-Python: >=3.10
